libdouya/__init__.py
libdouya/core/__init__.py
libdouya/core/app/__init__.py
libdouya/core/app/application.py
libdouya/core/deco/__init__.py
libdouya/core/deco/configer.py
libdouya/core/deco/naming.py
libdouya/core/hook/__init__.py
libdouya/core/hook/db/__init__.py
libdouya/core/hook/err/__init__.py
libdouya/core/mgr/__init__.py
libdouya/core/mgr/configuration/__init__.py
libdouya/core/mgr/configuration/configuration_mgr.py
libdouya/core/mgr/configuration/constant.py
libdouya/core/mgr/datacache/__init__.py
libdouya/core/mgr/datacache/datacache_mgr.py
libdouya/core/mgr/datacache/error/__init__.py
libdouya/core/mgr/datacache/error/error_datacache.py
libdouya/core/mgr/naming/__init__.py
libdouya/core/mgr/naming/naming_mgr.py
libdouya/core/rdb/__init__.py
libdouya/core/rdb/orm/__init__.py
libdouya/core/rdb/orm/pony_database.py
libdouya/core/rdb/orm/sql_alchemy_database.py
libdouya/core/rdb/orm/parent/__init__.py
libdouya/core/rdb/orm/parent/base_database.py
libdouya/core/srv/__init__.py
libdouya/core/srv/service_task.py
libdouya/core/srv/service_worker.py
libdouya/core/srv/runner/__init__.py
libdouya/core/srv/runner/service_process_runner.py
libdouya/core/srv/runner/service_thread_runner.py
libdouya/core/srv/runner/parent/__init__.py
libdouya/core/srv/runner/parent/service_base_runner.py
libdouya/core/utilities/__init__.py
libdouya/core/utilities/configer.py
libdouya/dataclasses/__init__.py
libdouya/dataclasses/c/__init__.py
libdouya/dataclasses/c/cfg/__init__.py
libdouya/dataclasses/c/cfg/database_configer.py
libdouya/dataclasses/c/cfg/datacache_configer.py
libdouya/dataclasses/c/cfg/service_configer.py
libdouya/dataclasses/c/cfg/parent/__init__.py
libdouya/dataclasses/c/cfg/parent/base_configer.py
libdouya/dataclasses/c/concurrency/__init__.py
libdouya/dataclasses/c/concurrency/sleeper.py
libdouya/dataclasses/c/concurrency/thread.py
libdouya/dataclasses/c/db/__init__.py
libdouya/dataclasses/c/db/databases.py
libdouya/dataclasses/c/err/__init__.py
douya-0.0.1a0.dist-info/LICENSE
douya-0.0.1a0.dist-info/METADATA
douya-0.0.1a0.dist-info/WHEEL
douya-0.0.1a0.dist-info/top_level.txt
douya-0.0.1a0.dist-info/RECORD
